monologue/__init__.py
monologue/admin.py
monologue/forms.py
monologue/migrations/0001_initial.py
monologue/migrations/__init__.py
monologue/models.py
monologue/static/bootstrap.css
monologue/static/bootstrap.js
monologue/static/jquery-3.5.1.slim.js
monologue/static/popper.js
monologue/templates/base.html
monologue/templates/index.html
monologue/templates/post.html
monologue/urls.py
monologue/views.py
django_monologue-0.1.0.dist-info/LICENSE
django_monologue-0.1.0.dist-info/WHEEL
django_monologue-0.1.0.dist-info/METADATA
django_monologue-0.1.0.dist-info/RECORD
